odoo8_addon_partner_contact_company-8.0.1.0.0.99.dev1-py3.8-nspkg.pth
odoo_addons/partner_contact_company/README.rst
odoo_addons/partner_contact_company/__init__.py
odoo_addons/partner_contact_company/__openerp__.py
odoo_addons/partner_contact_company/models/__init__.py
odoo_addons/partner_contact_company/models/partner.py
odoo_addons/partner_contact_company/views/partner_view.xml
odoo8_addon_partner_contact_company-8.0.1.0.0.99.dev1.dist-info/METADATA
odoo8_addon_partner_contact_company-8.0.1.0.0.99.dev1.dist-info/WHEEL
odoo8_addon_partner_contact_company-8.0.1.0.0.99.dev1.dist-info/namespace_packages.txt
odoo8_addon_partner_contact_company-8.0.1.0.0.99.dev1.dist-info/top_level.txt
odoo8_addon_partner_contact_company-8.0.1.0.0.99.dev1.dist-info/RECORD
